filetree/__init__.py
filetree/funcs.py
filetree/tree.py
filetree-0.3.5.dist-info/DESCRIPTION.rst
filetree-0.3.5.dist-info/METADATA
filetree-0.3.5.dist-info/RECORD
filetree-0.3.5.dist-info/WHEEL
filetree-0.3.5.dist-info/metadata.json
filetree-0.3.5.dist-info/top_level.txt
